LICENSE
README.md
setup.py
configs/__init__.py
configs/_base_/__init__.py
tools/__init__.py
trademaster407/__init__.py
trademaster407.egg-info/PKG-INFO
trademaster407.egg-info/SOURCES.txt
trademaster407.egg-info/dependency_links.txt
trademaster407.egg-info/requires.txt
trademaster407.egg-info/top_level.txt
trademaster407/agents/__init__.py
trademaster407/agents/builder.py
trademaster407/agents/custom.py
trademaster407/agents/algorithmic_trading/__init__.py
trademaster407/agents/algorithmic_trading/dqn.py
trademaster407/agents/high_frequency_trading/__init__.py
trademaster407/agents/high_frequency_trading/ddqn.py
trademaster407/agents/order_execution/__init__.py
trademaster407/agents/order_execution/eteo.py
trademaster407/agents/order_execution/pd.py
trademaster407/agents/portfolio_management/__init__.py
trademaster407/agents/portfolio_management/deeptrader.py
trademaster407/agents/portfolio_management/eiie.py
trademaster407/agents/portfolio_management/investor_imitator.py
trademaster407/collector/__init__.py
trademaster407/collector/binance.py
trademaster407/collector/builder.py
trademaster407/collector/custom.py
trademaster407/collector/helper/__init__.py
trademaster407/collector/helper/celery_app.py
trademaster407/collector/helper/celery_config.py
trademaster407/collector/helper/pika_connection.py
trademaster407/collector/helper/run_celery.py
trademaster407/collector/helper/websocket_consumer.py
trademaster407/collector/helper/websocket_producer.py
trademaster407/datasets/__init__.py
trademaster407/datasets/builder.py
trademaster407/datasets/custom.py
trademaster407/datasets/algorithmic_trading/__init__.py
trademaster407/datasets/algorithmic_trading/dataset.py
trademaster407/datasets/high_frequency_trading/__init__.py
trademaster407/datasets/high_frequency_trading/dataset.py
trademaster407/datasets/order_execution/__init__.py
trademaster407/datasets/order_execution/dataset.py
trademaster407/datasets/portfolio_management/__init__.py
trademaster407/datasets/portfolio_management/dataset.py
trademaster407/environments/__init__.py
trademaster407/environments/builder.py
trademaster407/environments/custom.py
