Metadata-Version: 2.1
Name: trademaster407
Version: 0.0.1
Summary: TradeMaster - A platform for algorithmic trading
Home-page: https://github.com/TradeMaster-NTU/TradeMaster
Author: NTU_trademaster
Author-email: TradeMaster.NTU@gmail.com
License: UNKNOWN
Platform: UNKNOWN
Classifier: Programming Language :: Python :: 3
Classifier: License :: OSI Approved :: MIT License
Classifier: Operating System :: OS Independent
License-File: LICENSE
